Progetto_di_sistemi_a_sensore/D_Latch_sincrono/Dlatch.vhdl
entity Dlatch is
	port(D, Clk : in bit;
		Q : out bit);
end entity Dlatch;

architecture Beh of Dlatch is
	begin
		process(D, Clk)
		begin
			if Clk='1' and Clk'Event then
				Q <= D after 3 ns;
			end if;
		end process;
end architecture Beh;

Progetto_di_sistemi_a_sensore/D_Latch_sincrono/And2.vhdl
entity And2 is
	port(In1, In2: in bit;
		Out1: out bit);
end entity And2;

architecture Beh of And2 is
	begin
		Out1 <= In1 and In2 after 2 ns;
end architecture Beh;

Progetto_di_sistemi_a_sensore/D_Latch_sincrono/Dlatch_En.vhdl
entity Dlatch_En is
	port(Din, Clk, En : in bit;
		Qout : out bit);
end entity Dlatch_En;

architecture Struct of Dlatch_En is
	signal IntClk : bit;
	begin
		gate: entity work.And2 port map(In1 => Clk, In2 => En, Out1 => IntClk);
		latch: entity work.Dlatch(Beh) port map(Clk => IntClk, D => Din, Q => Qout);
end architecture Struct;

Progetto_di_sistemi_a_sensore/D_Latch_sincrono/output.vcd
$date
  Sat Jan 15 16:44:43 2022
$end
$version
  GHDL v0
$end
$timescale
  1 fs
$end
$var reg 1 ! din $end
$var reg 1 " clk $end
$var reg 1 # en $end
$var reg 1 $ qout $end
$scope module dlatch_en $end
$var reg 1 % din $end
$var reg 1 & clk $end
$var reg 1 ' en $end
$var reg 1 ( qout $end
$var reg 1 ) intclk $end
$scope module gate $end
$var reg 1 * in1 $end
$var reg 1 + in2 $end
$var reg 1 , out1 $end
$upscope $end
$scope module latch $end
$var reg 1 - d $end
$var reg 1 . clk $end
$var reg 1 / q $end
$upscope $end
$upscope $end
$enddefinitions $end
#0
0!
0"
0#
0$
0%
0&
0'
0(
0)
0*
0+
0,
0-
0.
0/
#2000000
0,
#500000000000
1"
1&
1*
#500002000000
0,
#1000000000000
0"
0&
0*
#1000002000000
0,
#1500000000000
1"
1&
1*
#1500002000000
0,
#2000000000000
0"
0&
0*
#2000002000000
0,
#2500000000000
1"
1&
1*
#2500002000000
0,
#3000000000000
0"
0&
0*
#3000002000000
0,
#3500000000000
1"
1&
1*
#3500002000000
0,
#4000000000000
0"
0&
0*
#4000002000000
0,
#4500000000000
1"
1&
1*
#4500002000000
0,
#5000000000000
0"
0&
0*
#5000002000000
0,
#5500000000000
1"
1&
1*
#5500002000000
0,
#6000000000000
0"
0&
0*
#6000002000000
0,
#6500000000000
1"
1&
1*
#6500002000000
0,
#7000000000000
0"
0&
0*
#7000002000000
0,
#7500000000000
1"
1&
1*
#7500002000000
0,
#8000000000000
0"
0&
0*
#8000002000000
0,
#8500000000000
1"
1&
1*
#8500002000000
0,
#9000000000000
0"
0&
0*
#9000002000000
0,
#9500000000000
1"
1&
1*
#9500002000000
0,
#10000000000000
0"
0&
0*
#10000002000000
0,
#10500000000000
1"
1&
1*
#10500002000000
0,
#11000000000000
0"
0&
0*
#11000002000000
0,
#11500000000000
1"
1&
1*
#11500002000000
0,
#12000000000000
0"
0&
0*
#12000002000000
0,
#12500000000000
1"
1&
1*
#12500002000000
0,
#13000000000000
0"
0&
0*
#13000002000000
0,
#13500000000000
1"
1&
1*
#13500002000000
0,
#14000000000000
0"
0&
0*
#14000002000000
0,
#14500000000000
1"
1&
1*
#14500002000000
0,
#15000000000000
0"
0&
0*
#15000002000000
0,
#15500000000000
1"
1&
1*
#15500002000000
0,
#16000000000000
0"
0&
0*
#16000002000000
0,
#16500000000000
1"
1&
1*
#16500002000000
0,
#17000000000000
0"
0&
0*
#17000002000000
0,
#17500000000000
1"
1&
1*
#17500002000000
0,
#18000000000000
0"
0&
0*
#18000002000000
0,
#18500000000000
1"
1&
1*
#18500002000000
0,
#19000000000000
0"
0&
0*
#19000002000000
0,
#19500000000000
1"
1&
1*
#19500002000000
0,
#20000000000000
0"
1#
0&
1'
0*
1+
#20000002000000
0,
#20500000000000
1"
1&
1*
#20500002000000
1)
1,
1.
#20500005000000
0(
0/
#21000000000000
0"
0&
0*
#21000002000000
0)
0,
0.
#21500000000000
1"
1&
1*
#21500002000000
1)
1,
1.
#21500005000000
0(
0/
#22000000000000
0"
0&
0*
#22000002000000
0)
0,
0.
#22500000000000
1"
1&
1*
#22500002000000
1)
1,
1.
#22500005000000
0(
0/
#23000000000000
0"
0&
0*
#23000002000000
0)
0,
0.
#23500000000000
1"
1&
1*
#23500002000000
1)
1,
1.
#23500005000000
0(
0/
#24000000000000
0"
0&
0*
#24000002000000
0)
0,
0.
#24500000000000
1"
1&
1*
#24500002000000
1)
1,
1.
#24500005000000
0(
0/
#25000000000000
0"
0&
0*
#25000002000000
0)
0,
0.
#25500000000000
1"
1&
1*
#25500002000000
1)
1,
1.
#25500005000000
0(
0/
#26000000000000
0"
0&
0*
#26000002000000
0)
0,
0.
#26500000000000
1"
1&
1*
#26500002000000
1)
1,
1.
#26500005000000
0(
0/
#27000000000000
0"
0&
0*
#27000002000000
0)
0,
0.
#27500000000000
1"
1&
1*
#27500002000000
1)
1,
1.
#27500005000000
0(
0/
#28000000000000
0"
0&
0*
#28000002000000
0)
0,
0.
#28500000000000
1"
1&
1*
#28500002000000
1)
1,
1.
#28500005000000
0(
0/
#29000000000000
0"
0&
0*
#29000002000000
0)
0,
0.
#29500000000000
1"
1&
1*
#29500002000000
1)
1,
1.
#29500005000000
0(
0/
#30000000000000
0"
0&
0*
#30000002000000
0)
0,
0.
#30500000000000
1"
1&
1*
#30500002000000
1)
1,
1.
#30500005000000
0(
0/
#31000000000000
0"
0&
0*
#31000002000000
0)
0,
0.
#31500000000000
1"
1&
1*
#31500002000000
1)
1,
1.
#31500005000000
0(
0/
#32000000000000
0"
0&
0*
#32000002000000
0)
0,
0.
#32500000000000
1"
1&
1*
#32500002000000
1)
1,
1.
#32500005000000
0(
0/
#33000000000000
0"
0&
0*
#33000002000000
0)
0,
0.
#33500000000000
1"
1&
1*
#33500002000000
1)
1,
1.
#33500005000000
0(
0/
#34000000000000
0"
0&
0*
#34000002000000
0)
0,
0.
#34500000000000
1"
1&
1*
#34500002000000
1)
1,
1.
#34500005000000
0(
0/
#35000000000000
0"
0&
0*
#35000002000000
0)
0,
0.
#35500000000000
1"
1&
1*
#35500002000000
1)
1,
1.
#35500005000000
0(
0/
#36000000000000
0"
0&
0*
#36000002000000
0)
0,
0.
#36500000000000
1"
1&
1*
#36500002000000
1)
1,
1.
#36500005000000
0(
0/
#37000000000000
0"
0&
0*
#37000002000000
0)
0,
0.
#37500000000000
1"
1&
1*
#37500002000000
1)
1,
1.
#37500005000000
0(
0/
#38000000000000
0"
0&
0*
#38000002000000
0)
0,
0.
#38500000000000
1"
1&
1*
#38500002000000
1)
1,
1.
#38500005000000
0(
0/
#39000000000000
0"
0&
0*
#39000002000000
0)
0,
0.
#39500000000000
1"
1&
1*
#39500002000000
1)
1,
1.
#39500005000000
0(
0/
#40000000000000
0"
0&
0*
#40000002000000
0)
0,
0.
#40500000000000
1"
1&
1*
#40500002000000
1)
1,
1.
#40500005000000
0(
0/
#41000000000000
0"
0&
0*
#41000002000000
0)
0,
0.
#41500000000000
1"
1&
1*
#41500002000000
1)
1,
1.
#41500005000000
0(
0/
#42000000000000
0"
0&
0*
#42000002000000
0)
0,
0.
#42500000000000
1"
1&
1*
#42500002000000
1)
1,
1.
#42500005000000
0(
0/
#43000000000000
0"
0&
0*
#43000002000000
0)
0,
0.
#43500000000000
1"
1&
1*
#43500002000000
1)
1,
1.
#43500005000000
0(
0/
#44000000000000
0"
0&
0*
#44000002000000
0)
0,
0.
#44500000000000
1"
1&
1*
#44500002000000
1)
1,
1.
#44500005000000
0(
0/
#45000000000000
0"
0&
0*
#45000002000000
0)
0,
0.
#45500000000000
1"
1&
1*
#45500002000000
1)
1,
1.
#45500005000000
0(
0/
#46000000000000
0"
0&
0*
#46000002000000
0)
0,
0.
#46500000000000
1"
1&
1*
#46500002000000
1)
1,
1.
#46500005000000
0(
0/
#47000000000000
0"
0&
0*
#47000002000000
0)
0,
0.
#47500000000000
1"
1&
1*
#47500002000000
1)
1,
1.
#47500005000000
0(
0/
#48000000000000
0"
0&
0*
#48000002000000
0)
0,
0.
#48500000000000
1"
1&
1*
#48500002000000
1)
1,
1.
#48500005000000
0(
0/
#49000000000000
0"
0&
0*
#49000002000000
0)
0,
0.
#49500000000000
1"
1&
1*
#49500002000000
1)
1,
1.
#49500005000000
0(
0/
#50000000000000
1!
0"
1%
0&
0*
1-
#50000002000000
0)
0,
0.
#50500000000000
1"
1&
1*
#50500002000000
1)
1,
1.
#50500005000000
1$
1(
1/
#51000000000000
0"
0&
0*
#51000002000000
0)
0,
0.
#51500000000000
1"
1&
1*
#51500002000000
1)
1,
1.
#51500005000000
1(
1/
#52000000000000
0"
0&
0*
#52000002000000
0)
0,
0.
#52500000000000
1"
1&
1*
#52500002000000
1)
1,
1.
#52500005000000
1(
1/
#53000000000000
0"
0&
0*
#53000002000000
0)
0,
0.
#53500000000000
1"
1&
1*
#53500002000000
1)
1,
1.
#53500005000000
1(
1/
#54000000000000
0"
0&
0*
#54000002000000
0)
0,
0.
#54500000000000
1"
1&
1*
#54500002000000
1)
1,
1.
#54500005000000
1(
1/
#55000000000000
0"
0&
0*
#55000002000000
0)
0,
0.
#55500000000000
1"
1&
1*
#55500002000000
1)
1,
1.
#55500005000000
1(
1/
#56000000000000
0"
0&
0*
#56000002000000
0)
0,
0.
#56500000000000
1"
1&
1*
#56500002000000
1)
1,
1.
#56500005000000
1(
1/
#57000000000000
0"
0&
0*
#57000002000000
0)
0,
0.
#57500000000000
1"
1&
1*
#57500002000000
1)
1,
1.
#57500005000000
1(
1/
#58000000000000
0"
0&
0*
#58000002000000
0)
0,
0.
#58500000000000
1"
1&
1*
#58500002000000
1)
1,
1.
#58500005000000
1(
1/
#59000000000000
0"
0&
0*
#59000002000000
0)
0,
0.
#59500000000000
1"
1&
1*
#59500002000000
1)
1,
1.
#59500005000000
1(
1/
#60000000000000
0"
0&
0*
#60000002000000
0)
0,
0.
#60500000000000
1"
1&
1*
#60500002000000
1)
1,
1.
#60500005000000
1(
1/
#61000000000000
0"
0&
0*
#61000002000000
0)
0,
0.
#61500000000000
1"
1&
1*
#61500002000000
1)
1,
1.
#61500005000000
1(
1/
#62000000000000
0"
0&
0*
#62000002000000
0)
0,
0.
#62500000000000
1"
1&
1*
#62500002000000
1)
1,
1.
#62500005000000
1(
1/
#63000000000000
0"
0&
0*
#63000002000000
0)
0,
0.
#63500000000000
1"
1&
1*
#63500002000000
1)
1,
1.
#63500005000000
1(
1/
#64000000000000
0"
0&
0*
#64000002000000
0)
0,
0.
#64500000000000
1"
1&
1*
#64500002000000
1)
1,
1.
#64500005000000
1(
1/
#65000000000000
0"
0&
0*
#65000002000000
0)
0,
0.
#65500000000000
1"
1&
1*
#65500002000000
1)
1,
1.
#65500005000000
1(
1/
#66000000000000
0"
0&
0*
#66000002000000
0)
0,
0.
#66500000000000
1"
1&
1*
#66500002000000
1)
1,
1.
#66500005000000
1(
1/
#67000000000000
0"
0&
0*
#67000002000000
0)
0,
0.
#67500000000000
1"
1&
1*
#67500002000000
1)
1,
1.
#67500005000000
1(
1/
#68000000000000
0"
0&
0*
#68000002000000
0)
0,
0.
#68500000000000
1"
1&
1*
#68500002000000
1)
1,
1.
#68500005000000
1(
1/
#69000000000000
0"
0&
0*
#69000002000000
0)
0,
0.
#69500000000000
1"
1&
1*
#69500002000000
1)
1,
1.
#69500005000000
1(
1/
#70000000000000
0"
0&
0*
#70000002000000
0)
0,
0.
#70500000000000
1"
1&
1*
#70500002000000
1)
1,
1.
#70500005000000
1(
1/
#71000000000000
0"
0&
0*
#71000002000000
0)
0,
0.
#71500000000000
1"
1&
1*
#71500002000000
1)
1,
1.
#71500005000000
1(
1/
#72000000000000
0"
0&
0*
#72000002000000
0)
0,
0.
#72500000000000
1"
1&
1*
#72500002000000
1)
1,
1.
#72500005000000
1(
1/
#73000000000000
0"
0&
0*
#73000002000000
0)
0,
0.
#73500000000000
1"
1&
1*
#73500002000000
1)
1,
1.
#73500005000000
1(
1/
#74000000000000
0"
0&
0*
#74000002000000
0)
0,
0.
#74500000000000
1"
1&
1*
#74500002000000
1)
1,
1.
#74500005000000
1(
1/
#75000000000000
0"
0&
0*
#75000002000000
0)
0,
0.
#75500000000000
1"
1&
1*
#75500002000000
1)
1,
1.
#75500005000000
1(
1/
#76000000000000
0"
0&
0*
#76000002000000
0)
0,
0.
#76500000000000
1"
1&
1*
#76500002000000
1)
1,
1.
#76500005000000
1(
1/
#77000000000000
0"
0&
0*
#77000002000000
0)
0,
0.
#77500000000000
1"
1&
1*
#77500002000000
1)
1,
1.
#77500005000000
1(
1/
#78000000000000
0"
0&
0*
#78000002000000
0)
0,
0.
#78500000000000
1"
1&
1*
#78500002000000
1)
1,
1.
#78500005000000
1(
1/
#79000000000000
0"
0&
0*
#79000002000000
0)
0,
0.
#79500000000000
1"
1&
1*
#79500002000000
1)
1,
1.
#79500005000000
1(
1/
#80000000000000
0"
0&
0*
#80000002000000
0)
0,
0.
#80500000000000
1"
1&
1*
#80500002000000
1)
1,
1.
#80500005000000
1(
1/
#81000000000000
0"
0&
0*
#81000002000000
0)
0,
0.
#81500000000000
1"
1&
1*
#81500002000000
1)
1,
1.
#81500005000000
1(
1/
#82000000000000
0"
0&
0*
#82000002000000
0)
0,
0.
#82500000000000
1"
1&
1*
#82500002000000
1)
1,
1.
#82500005000000
1(
1/
#83000000000000
0"
0&
0*
#83000002000000
0)
0,
0.
#83500000000000
1"
1&
1*
#83500002000000
1)
1,
1.
#83500005000000
1(
1/
#84000000000000
0"
0&
0*
#84000002000000
0)
0,
0.
#84500000000000
1"
1&
1*
#84500002000000
1)
1,
1.
#84500005000000
1(
1/
#85000000000000
0"
0&
0*
#85000002000000
0)
0,
0.
#85500000000000
1"
1&
1*
#85500002000000
1)
1,
1.
#85500005000000
1(
1/
#86000000000000
0"
0&
0*
#86000002000000
0)
0,
0.
#86500000000000
1"
1&
1*
#86500002000000
1)
1,
1.
#86500005000000
1(
1/
#87000000000000
0"
0&
0*
#87000002000000
0)
0,
0.
#87500000000000
1"
1&
1*
#87500002000000
1)
1,
1.
#87500005000000
1(
1/
#88000000000000
0"
0&
0*
#88000002000000
0)
0,
0.
#88500000000000
1"
1&
1*
#88500002000000
1)
1,
1.
#88500005000000
1(
1/
#89000000000000
0"
0&
0*
#89000002000000
0)
0,
0.
#89500000000000
1"
1&
1*
#89500002000000
1)
1,
1.
#89500005000000
1(
1/
#90000000000000
0"
0#
0&
0'
0*
0+
#90000002000000
0)
0,
0.
#90500000000000
1"
1&
1*
#90500002000000
0,
#91000000000000
0"
0&
0*
#91000002000000
0,
#91500000000000
1"
1&
1*
#91500002000000
0,
#92000000000000
0"
0&
0*
#92000002000000
0,
#92500000000000
1"
1&
1*
#92500002000000
0,
#93000000000000
0"
0&
0*
#93000002000000
0,
#93500000000000
1"
1&
1*
#93500002000000
0,
#94000000000000
0"
0&
0*
#94000002000000
0,
#94500000000000
1"
1&
1*
#94500002000000
0,
#95000000000000
0"
0&
0*
#95000002000000
0,
#95500000000000
1"
1&
1*
#95500002000000
0,
#96000000000000
0"
0&
0*
#96000002000000
0,
#96500000000000
1"
1&
1*
#96500002000000
0,
#97000000000000
0"
0&
0*
#97000002000000
0,
#97500000000000
1"
1&
1*
#97500002000000
0,
#98000000000000
0"
0&
0*
#98000002000000
0,
#98500000000000
1"
1&
1*
#98500002000000
0,
#99000000000000
0"
0&
0*
#99000002000000
0,
#99500000000000
1"
1&
1*
#99500002000000
0,
#100000000000000
0!
0"
0%
0&
0*
0-
#100000002000000
0,
#100500000000000
1"
1&
1*
#100500002000000
0,
#101000000000000
0"
0&
0*
#101000002000000
0,
#101500000000000
1"
1&
1*
#101500002000000
0,
#102000000000000
0"
0&
0*
#102000002000000
0,
#102500000000000
1"
1&
1*
#102500002000000
0,
#103000000000000
0"
0&
0*
#103000002000000
0,
#103500000000000
1"
1&
1*
#103500002000000
0,
#104000000000000
0"
0&
0*
#104000002000000
0,
#104500000000000
1"
1&
1*
#104500002000000
0,
#105000000000000
0"
0&
0*
#105000002000000
0,
#105500000000000
1"
1&
1*
#105500002000000
0,
#106000000000000
0"
0&
0*
#106000002000000
0,
#106500000000000
1"
1&
1*
#106500002000000
0,
#107000000000000
0"
0&
0*
#107000002000000
0,
#107500000000000
1"
1&
1*
#107500002000000
0,
#108000000000000
0"
0&
0*
#108000002000000
0,
#108500000000000
1"
1&
1*
#108500002000000
0,
#109000000000000
0"
0&
0*
#109000002000000
0,
#109500000000000
1"
1&
1*
#109500002000000
0,
#110000000000000
0"
0&
0*
#110000002000000
0,
#110500000000000
1"
1&
1*
#110500002000000
0,
#111000000000000
0"
0&
0*
#111000002000000
0,
#111500000000000
1"
1&
1*
#111500002000000
0,
#112000000000000
0"
0&
0*
#112000002000000
0,
#112500000000000
1"
1&
1*
#112500002000000
0,
#113000000000000
0"
0&
0*
#113000002000000
0,
#113500000000000
1"
1&
1*
#113500002000000
0,
#114000000000000
0"
0&
0*
#114000002000000
0,
#114500000000000
1"
1&
1*
#114500002000000
0,
#115000000000000
0"
1#
0&
1'
0*
1+
#115000002000000
0,
#115500000000000
1"
1&
1*
#115500002000000
1)
1,
1.
#115500005000000
0$
0(
0/
#116000000000000
0"
0&
0*
#116000002000000
0)
0,
0.
#116500000000000
1"
1&
1*
#116500002000000
1)
1,
1.
#116500005000000
0(
0/
#117000000000000
0"
0&
0*
#117000002000000
0)
0,
0.
#117500000000000
1"
1&
1*
#117500002000000
1)
1,
1.
#117500005000000
0(
0/
#118000000000000
0"
0&
0*
#118000002000000
0)
0,
0.
#118500000000000
1"
1&
1*
#118500002000000
1)
1,
1.
#118500005000000
0(
0/
#119000000000000
0"
0&
0*
#119000002000000
0)
0,
0.
#119500000000000
1"
1&
1*
#119500002000000
1)
1,
1.
#119500005000000
0(
0/
#120000000000000
0"
0&
0*
#120000002000000
0)
0,
0.
#120500000000000
1"
1&
1*
#120500002000000
1)
1,
1.
#120500005000000
0(
0/
#121000000000000
0"
0&
0*
#121000002000000
0)
0,
0.
#121500000000000
1"
1&
1*
#121500002000000
1)
1,
1.
#121500005000000
0(
0/
#122000000000000
0"
0&
0*
#122000002000000
0)
0,
0.
#122500000000000
1"
1&
1*
#122500002000000
1)
1,
1.
#122500005000000
0(
0/
#123000000000000
0"
0&
0*
#123000002000000
0)
0,
0.
#123500000000000
1"
1&
1*
#123500002000000
1)
1,
1.
#123500005000000
0(
0/
#124000000000000
0"
0&
0*
#124000002000000
0)
0,
0.
#124500000000000
1"
1&
1*
#124500002000000
1)
1,
1.
#124500005000000
0(
0/
#125000000000000
0"
0&
0*
#125000002000000
0)
0,
0.
#125500000000000
1"
1&
1*
#125500002000000
1)
1,
1.
#125500005000000
0(
0/
#126000000000000
0"
0&
0*
#126000002000000
0)
0,
0.
#126500000000000
1"
1&
1*
#126500002000000
1)
1,
1.
#126500005000000
0(
0/
#127000000000000
0"
0&
0*
#127000002000000
0)
0,
0.
#127500000000000
1"
1&
1*
#127500002000000
1)
1,
1.
#127500005000000
0(
0/
#128000000000000
0"
0&
0*
#128000002000000
0)
0,
0.
#128500000000000
1"
1&
1*
#128500002000000
1)
1,
1.
#128500005000000
0(
0/
#129000000000000
0"
0&
0*
#129000002000000
0)
0,
0.
#129500000000000
1"
1&
1*
#129500002000000
1)
1,
1.
#129500005000000
0(
0/
#130000000000000
0"
0&
0*
#130000002000000
0)
0,
0.
#130500000000000
1"
1&
1*
#130500002000000
1)
1,
1.
#130500005000000
0(
0/
#131000000000000
0"
0&
0*
#131000002000000
0)
0,
0.
#131500000000000
1"
1&
1*
#131500002000000
1)
1,
1.
#131500005000000
0(
0/
#132000000000000
0"
0&
0*
#132000002000000
0)
0,
0.
#132500000000000
1"
1&
1*
#132500002000000
1)
1,
1.
#132500005000000
0(
0/
#133000000000000
0"
0&
0*
#133000002000000
0)
0,
0.
#133500000000000
1"
1&
1*
#133500002000000
1)
1,
1.
#133500005000000
0(
0/
#134000000000000
0"
0&
0*
#134000002000000
0)
0,
0.
#134500000000000
1"
1&
1*
#134500002000000
1)
1,
1.
#134500005000000
0(
0/
#135000000000000
0"
0&
0*
#135000002000000
0)
0,
0.
#135500000000000
1"
1&
1*
#135500002000000
1)
1,
1.
#135500005000000
0(
0/
#136000000000000
0"
0&
0*
#136000002000000
0)
0,
0.
#136500000000000
1"
1&
1*
#136500002000000
1)
1,
1.
#136500005000000
0(
0/
#137000000000000
0"
0&
0*
#137000002000000
0)
0,
0.
#137500000000000
1"
1&
1*
#137500002000000
1)
1,
1.
#137500005000000
0(
0/
#138000000000000
0"
0&
0*
#138000002000000
0)
0,
0.
#138500000000000
1"
1&
1*
#138500002000000
1)
1,
1.
#138500005000000
0(
0/
#139000000000000
0"
0&
0*
#139000002000000
0)
0,
0.
#139500000000000
1"
1&
1*
#139500002000000
1)
1,
1.
#139500005000000
0(
0/
#140000000000000
0"
0&
0*
#140000002000000
0)
0,
0.
#140500000000000
1"
1&
1*
#140500002000000
1)
1,
1.
#140500005000000
0(
0/
#141000000000000
0"
0&
0*
#141000002000000
0)
0,
0.
#141500000000000
1"
1&
1*
#141500002000000
1)
1,
1.
#141500005000000
0(
0/
#142000000000000
0"
0&
0*
#142000002000000
0)
0,
0.
#142500000000000
1"
1&
1*
#142500002000000
1)
1,
1.
#142500005000000
0(
0/
#143000000000000
0"
0&
0*
#143000002000000
0)
0,
0.
#143500000000000
1"
1&
1*
#143500002000000
1)
1,
1.
#143500005000000
0(
0/
#144000000000000
0"
0&
0*
#144000002000000
0)
0,
0.
#144500000000000
1"
1&
1*
#144500002000000
1)
1,
1.
#144500005000000
0(
0/
#145000000000000
0"
0&
0*
#145000002000000
0)
0,
0.
#145500000000000
1"
1&
1*
#145500002000000
1)
1,
1.
#145500005000000
0(
0/
#146000000000000
0"
0&
0*
#146000002000000
0)
0,
0.
#146500000000000
1"
1&
1*
#146500002000000
1)
1,
1.
#146500005000000
0(
0/
#147000000000000
0"
0&
0*
#147000002000000
0)
0,
0.
#147500000000000
1"
1&
1*
#147500002000000
1)
1,
1.
#147500005000000
0(
0/
#148000000000000
0"
0&
0*
#148000002000000
0)
0,
0.
#148500000000000
1"
1&
1*
#148500002000000
1)
1,
1.
#148500005000000
0(
0/
#149000000000000
0"
0&
0*
#149000002000000
0)
0,
0.
#149500000000000
1"
1&
1*
#149500002000000
1)
1,
1.
#149500005000000
0(
0/
#150000000000000
0"
0&
0*
#150000002000000
0)
0,
0.
#150500000000000
1"
1&
1*
#150500002000000
1)
1,
1.
#150500005000000
0(
0/
#151000000000000
0"
0&
0*
#151000002000000
0)
0,
0.
#151500000000000
1"
1&
1*
#151500002000000
1)
1,
1.
#151500005000000
0(
0/
#152000000000000
0"
0&
0*
#152000002000000
0)
0,
0.
#152500000000000
1"
1&
1*
#152500002000000
1)
1,
1.
#152500005000000
0(
0/
#153000000000000
0"
0&
0*
#153000002000000
0)
0,
0.
#153500000000000
1"
1&
1*
#153500002000000
1)
1,
1.
#153500005000000
0(
0/
#154000000000000
0"
0&
0*
#154000002000000
0)
0,
0.
#154500000000000
1"
1&
1*
#154500002000000
1)
1,
1.
#154500005000000
0(
0/
#155000000000000
0"
0&
0*
#155000002000000
0)
0,
0.
#155500000000000
1"
1&
1*
#155500002000000
1)
1,
1.
#155500005000000
0(
0/
#156000000000000
0"
0&
0*
#156000002000000
0)
0,
0.
#156500000000000
1"
1&
1*
#156500002000000
1)
1,
1.
#156500005000000
0(
0/
#157000000000000
0"
0&
0*
#157000002000000
0)
0,
0.
#157500000000000
1"
1&
1*
#157500002000000
1)
1,
1.
#157500005000000
0(
0/
#158000000000000
0"
0&
0*
#158000002000000
0)
0,
0.
#158500000000000
1"
1&
1*
#158500002000000
1)
1,
1.
#158500005000000
0(
0/
#159000000000000
0"
0&
0*
#159000002000000
0)
0,
0.
#159500000000000
1"
1&
1*
#159500002000000
1)
1,
1.
#159500005000000
0(
0/
#160000000000000
0"
0&
0*
#160000002000000
0)
0,
0.
#160500000000000
1"
1&
1*
#160500002000000
1)
1,
1.
#160500005000000
0(
0/
#161000000000000
0"
0&
0*
#161000002000000
0)
0,
0.
#161500000000000
1"
1&
1*
#161500002000000
1)
1,
1.
#161500005000000
0(
0/
#162000000000000
0"
0&
0*
#162000002000000
0)
0,
0.
#162500000000000
1"
1&
1*
#162500002000000
1)
1,
1.
#162500005000000
0(
0/
#163000000000000
0"
0&
0*
#163000002000000
0)
0,
0.
#163500000000000
1"
1&
1*
#163500002000000
1)
1,
1.
#163500005000000
0(
0/
#164000000000000
0"
0&
0*
#164000002000000
0)
0,
0.
#164500000000000
1"
1&
1*
#164500002000000
1)
1,
1.
#164500005000000
0(
0/
#165000000000000
0"
0&
0*
#165000002000000
0)
0,
0.
#165500000000000
1"
1&
1*
#165500002000000
1)
1,
1.
#165500005000000
0(
0/
#166000000000000
0"
0&
0*
#166000002000000
0)
0,
0.
#166500000000000
1"
1&
1*
#166500002000000
1)
1,
1.
#166500005000000
0(
0/
#167000000000000
0"
0&
0*
#167000002000000
0)
0,
0.
#167500000000000
1"
1&
1*
#167500002000000
1)
1,
1.
#167500005000000
0(
0/
#168000000000000
0"
0&
0*
#168000002000000
0)
0,
0.
#168500000000000
1"
1&
1*
#168500002000000
1)
1,
1.
#168500005000000
0(
0/
#169000000000000
0"
0&
0*
#169000002000000
0)
0,
0.
#169500000000000
1"
1&
1*
#169500002000000
1)
1,
1.
#169500005000000
0(
0/
#170000000000000
0"
0&
0*
#170000002000000
0)
0,
0.
#170500000000000
1"
1&
1*
#170500002000000
1)
1,
1.
#170500005000000
0(
0/
#171000000000000
0"
0&
0*
#171000002000000
0)
0,
0.
#171500000000000
1"
1&
1*
#171500002000000
1)
1,
1.
#171500005000000
0(
0/
#172000000000000
0"
0&
0*
#172000002000000
0)
0,
0.
#172500000000000
1"
1&
1*
#172500002000000
1)
1,
1.
#172500005000000
0(
0/
#173000000000000
0"
0&
0*
#173000002000000
0)
0,
0.
#173500000000000
1"
1&
1*
#173500002000000
1)
1,
1.
#173500005000000
0(
0/
#174000000000000
0"
0&
0*
#174000002000000
0)
0,
0.
#174500000000000
1"
1&
1*
#174500002000000
1)
1,
1.
#174500005000000
0(
0/
#175000000000000
0"
0&
0*
#175000002000000
0)
0,
0.
#175500000000000
1"
1&
1*
#175500002000000
1)
1,
1.
#175500005000000
0(
0/
#176000000000000
0"
0&
0*
#176000002000000
0)
0,
0.
#176500000000000
1"
1&
1*
#176500002000000
1)
1,
1.
#176500005000000
0(
0/
#177000000000000
0"
0&
0*
#177000002000000
0)
0,
0.
#177500000000000
1"
1&
1*
#177500002000000
1)
1,
1.
#177500005000000
0(
0/
#178000000000000
0"
0&
0*
#178000002000000
0)
0,
0.
#178500000000000
1"
1&
1*
#178500002000000
1)
1,
1.
#178500005000000
0(
0/
#179000000000000
0"
0&
0*
#179000002000000
0)
0,
0.
#179500000000000
1"
1&
1*
#179500002000000
1)
1,
1.
#179500005000000
0(
0/
#180000000000000
0"
0&
0*
#180000002000000
0)
0,
0.
#180500000000000
1"
1&
1*
#180500002000000
1)
1,
1.
#180500005000000
0(
0/
#181000000000000
0"
0&
0*
#181000002000000
0)
0,
0.
#181500000000000
1"
1&
1*
#181500002000000
1)
1,
1.
#181500005000000
0(
0/
#182000000000000
0"
0&
0*
#182000002000000
0)
0,
0.
#182500000000000
1"
1&
1*
#182500002000000
1)
1,
1.
#182500005000000
0(
0/
#183000000000000
0"
0&
0*
#183000002000000
0)
0,
0.
#183500000000000
1"
1&
1*
#183500002000000
1)
1,
1.
#183500005000000
0(
0/
#184000000000000
0"
0&
0*
#184000002000000
0)
0,
0.
#184500000000000
1"
1&
1*
#184500002000000
1)
1,
1.
#184500005000000
0(
0/
#185000000000000
0"
0&
0*
#185000002000000
0)
0,
0.
#185500000000000
1"
1&
1*
#185500002000000
1)
1,
1.
#185500005000000
0(
0/
#186000000000000
0"
0&
0*
#186000002000000
0)
0,
0.
#186500000000000
1"
1&
1*
#186500002000000
1)
1,
1.
#186500005000000
0(
0/
#187000000000000
0"
0&
0*
#187000002000000
0)
0,
0.
#187500000000000
1"
1&
1*
#187500002000000
1)
1,
1.
#187500005000000
0(
0/
#188000000000000
0"
0&
0*
#188000002000000
0)
0,
0.
#188500000000000
1"
1&
1*
#188500002000000
1)
1,
1.
#188500005000000
0(
0/
#189000000000000
0"
0&
0*
#189000002000000
0)
0,
0.
#189500000000000
1"
1&
1*
#189500002000000
1)
1,
1.
#189500005000000
0(
0/
#190000000000000
0"
0&
0*
#190000002000000
0)
0,
0.
#190500000000000
1"
1&
1*
#190500002000000
1)
1,
1.
#190500005000000
0(
0/
#191000000000000
0"
0&
0*
#191000002000000
0)
0,
0.
#191500000000000
1"
1&
1*
#191500002000000
1)
1,
1.
#191500005000000
0(
0/
#192000000000000
0"
0&
0*
#192000002000000
0)
0,
0.
#192500000000000
1"
1&
1*
#192500002000000
1)
1,
1.
#192500005000000
0(
0/
#193000000000000
0"
0&
0*
#193000002000000
0)
0,
0.
#193500000000000
1"
1&
1*
#193500002000000
1)
1,
1.
#193500005000000
0(
0/
#194000000000000
0"
0&
0*
#194000002000000
0)
0,
0.
#194500000000000
1"
1&
1*
#194500002000000
1)
1,
1.
#194500005000000
0(
0/
#195000000000000
0"
0&
0*
#195000002000000
0)
0,
0.
#195500000000000
1"
1&
1*
#195500002000000
1)
1,
1.
#195500005000000
0(
0/
#196000000000000
0"
0&
0*
#196000002000000
0)
0,
0.
#196500000000000
1"
1&
1*
#196500002000000
1)
1,
1.
#196500005000000
0(
0/
#197000000000000
0"
0&
0*
#197000002000000
0)
0,
0.
